statemachine/__init__.py
statemachine/accesscontrol.py
statemachine/allows_access.py
statemachine/machine.py
statemachine/machineerror.py
statemachine/transitions.py
statemachine_elunico-1.0.0.dist-info/LICENSE
statemachine_elunico-1.0.0.dist-info/METADATA
statemachine_elunico-1.0.0.dist-info/WHEEL
statemachine_elunico-1.0.0.dist-info/entry_points.txt
statemachine_elunico-1.0.0.dist-info/top_level.txt
statemachine_elunico-1.0.0.dist-info/RECORD
