Metadata-Version: 2.1
Name: statemachine-elunico
Version: 1.0.0
Summary: Managing finite state machines around business logic with decorators
Home-page: https://github.com/elunico/Python-Finite-State-Machine
Author: Thomas Povinelli
Author-email: tompov227@gmail.com
License: Apache Software License 2.0
Keywords: decorators,state machine,finite state machine,python
Platform: UNKNOWN
Classifier: Development Status :: 3 - Alpha
Classifier: Intended Audience :: Developers
Classifier: License :: OSI Approved :: Apache Software License
Classifier: Natural Language :: English
Classifier: Programming Language :: Python :: 3.6
Classifier: Programming Language :: Python :: 3.7
Classifier: Programming Language :: Python :: 3.8
Requires-Python: >=3.6
